setup.py
python_simpledaemon.egg-info/PKG-INFO
python_simpledaemon.egg-info/SOURCES.txt
python_simpledaemon.egg-info/dependency_links.txt
python_simpledaemon.egg-info/top_level.txt
simpledaemon/__init__.py