Metadata-Version: 1.0
Name: python-simpledaemon
Version: 0.1
Summary: Easy Python Daemon
Home-page: https://github.com/gemini/python-simpledaemon
Author: Richard Hoop
Author-email: richard@projecticeland.net
License: GPLv3
Platform: UNKNOWN
